_switchboard.cpython-314-darwin.so
switchboard_hw-0.3.0.dist-info/RECORD
switchboard_hw-0.3.0.dist-info/WHEEL
switchboard_hw-0.3.0.dist-info/entry_points.txt
switchboard_hw-0.3.0.dist-info/top_level.txt
switchboard_hw-0.3.0.dist-info/METADATA
switchboard_hw-0.3.0.dist-info/licenses/LICENSE
switchboard/bitvector.py
switchboard/uart_xactor.py
switchboard/util.py
switchboard/axi.py
switchboard/sbdut.py
switchboard/cmdline.py
switchboard/__init__.py
switchboard/loopback.py
switchboard/umi.py
switchboard/warn.py
switchboard/verilator_run.py
switchboard/test_util.py
switchboard/ams.py
switchboard/autowrap.py
switchboard/switchboard.py
switchboard/gpio.py
switchboard/network.py
switchboard/xyce.py
switchboard/icarus.py
switchboard/sbdesign.py
switchboard/axil.py
switchboard/sbtcp.py
switchboard/pytest_plugin.py
switchboard/apb.py
switchboard/sc/__init__.py
switchboard/sc/standalone_netlist_flow.py
switchboard/sc/sed/__init__.py
switchboard/sc/sed/sed_remove.py
switchboard/sc/morty/uniquify.py
switchboard/sc/morty/__init__.py
switchboard/vpi/xyce_vpi.cc
switchboard/vpi/switchboard_vpi.cc
switchboard/dpi/switchboard_dpi.py
switchboard/dpi/xyce_dpi.cc
switchboard/dpi/__init__.py
switchboard/dpi/switchboard_dpi.cc
switchboard/verilog/__init__.py
switchboard/verilog/common/uart_xactor.sv
switchboard/verilog/common/__init__.py
switchboard/verilog/common/common.py
switchboard/verilog/common/switchboard.vh
switchboard/verilog/common/umi_gpio.v
switchboard/verilog/fpga/axi_writer.sv
switchboard/verilog/fpga/axi_reader.sv
switchboard/verilog/fpga/sb_rx_fpga.sv
switchboard/verilog/fpga/fpga.py
switchboard/verilog/fpga/sb_tx_fpga.sv
switchboard/verilog/fpga/config_registers.sv
switchboard/verilog/fpga/__init__.py
switchboard/verilog/fpga/memory_fault.sv
switchboard/verilog/fpga/umi_fpga_queues.sv
switchboard/verilog/fpga/sb_fpga_queues.sv
switchboard/verilog/fpga/include/spsc_queue.vh
switchboard/verilog/fpga/include/sb_queue_regmap.vh
switchboard/verilog/sim/umi_to_queue_sim.sv
switchboard/verilog/sim/sb_axi_m.sv
switchboard/verilog/sim/sb_axil_s.sv
switchboard/verilog/sim/sb_clk_gen.sv
switchboard/verilog/sim/auto_stop_sim.sv
switchboard/verilog/sim/xyce_intf.sv
