Metadata-Version: 2.4
Name: switchboard-hw
Version: 0.3.0
Summary: A low-latency communication library for RTL simulation and emulation.
Home-page: https://github.com/zeroasiccorp/switchboard
Author: Zero ASIC
License: Apache License 2.0
Project-URL: Documentation, https://zeroasiccorp.github.io/switchboard/
Project-URL: Bug Tracker, https://github.com/zeroasiccorp/switchboard/issues
Requires-Python: >=3.10
License-File: LICENSE
Requires-Dist: numpy
Requires-Dist: tqdm
Requires-Dist: siliconcompiler<0.36.0,>=0.35.3
Provides-Extra: test
Requires-Dist: pytest<10,>=8; extra == "test"
Requires-Dist: pytest-xdist; extra == "test"
Requires-Dist: pytest-timeout; extra == "test"
Provides-Extra: docs
Requires-Dist: sphinx; extra == "docs"
Requires-Dist: sphinx-rtd-theme; extra == "docs"
Requires-Dist: autodocsumm; extra == "docs"
Dynamic: author
Dynamic: description
Dynamic: description-content-type
Dynamic: home-page
Dynamic: license
Dynamic: license-file
Dynamic: project-url
Dynamic: provides-extra
Dynamic: requires-dist
Dynamic: requires-python
Dynamic: summary
